LightUI-1.0.1.data/scripts/entry.py
PyUi/__init__.py
PyUi/CLI/__init__.py
PyUi/CLI/manage.py
PyUi/CLI/Build/__init__.py
PyUi/CLI/Describe/__init__.py
PyUi/CLI/Describe/function.py
LightUI-1.0.1.dist-info/LICENSE
LightUI-1.0.1.dist-info/METADATA
LightUI-1.0.1.dist-info/WHEEL
LightUI-1.0.1.dist-info/top_level.txt
LightUI-1.0.1.dist-info/zip-safe
LightUI-1.0.1.dist-info/RECORD
