Metadata-Version: 2.1
Name: LightUI
Version: 1.0.1
Summary: A python UI DSL
Home-page: https://github.com/CleverCreator/PyUiDescribe
Author: CleverCreator
Author-email: liuhanbo333@icloud.com
License: MIT
Platform: Linux
Requires-Python: >=3.9
Requires-Dist: UNKnownDB (>=1.6.4)
Requires-Dist: UsefulHelper (>=1.7.3)
Requires-Dist: setuptools (>=52.0.0)
